Metadata-Version: 2.1
Name: diffengine
Version: 0.2.7
Summary: Monitor changes to webpages in RSS feeds
Home-page: UNKNOWN
Author: Ed Summers
Author-email: ehs@pobox.com
License: UNKNOWN
Platform: UNKNOWN
